src/__init__.py
src/pyhunter3.py
pyhunter3-0.1.3.dist-info/METADATA
pyhunter3-0.1.3.dist-info/WHEEL
pyhunter3-0.1.3.dist-info/entry_points.txt
pyhunter3-0.1.3.dist-info/top_level.txt
pyhunter3-0.1.3.dist-info/RECORD
