Metadata-Version: 2.1
Name: pyhunter3
Version: 0.1.3
Summary: Web pentesting framework
Home-page: https://github.com/mavedirra-01/pyhunter3
Author: mavedirra
Classifier: Programming Language :: Python :: 3
Classifier: License :: OSI Approved :: MIT License
Classifier: Operating System :: OS Independent
Requires-Python: >=3.6
Requires-Dist: paramiko
Requires-Dist: colorama
Requires-Dist: requests
Requires-Dist: markdown
